nx_neptune/__init__.py
nx_neptune/instance_management.py
nx_neptune/interface.py
nx_neptune/na_graph.py
nx_neptune/algorithms/__init__.py
nx_neptune/algorithms/centrality/__init__.py
nx_neptune/algorithms/centrality/closeness.py
nx_neptune/algorithms/centrality/degree_centrality.py
nx_neptune/algorithms/communities/__init__.py
nx_neptune/algorithms/communities/label_propagation.py
nx_neptune/algorithms/communities/louvain.py
nx_neptune/algorithms/link_analysis/__init__.py
nx_neptune/algorithms/link_analysis/pagerank.py
nx_neptune/algorithms/traversal/__init__.py
nx_neptune/algorithms/traversal/bfs.py
nx_neptune/algorithms/util/__init__.py
nx_neptune/algorithms/util/algorithm_utils.py
nx_neptune/clients/__init__.py
nx_neptune/clients/iam_client.py
nx_neptune/clients/na_client.py
nx_neptune/clients/na_models.py
nx_neptune/clients/neptune_constants.py
nx_neptune/clients/opencypher_builder.py
nx_neptune/utils/__init__.py
nx_neptune/utils/decorators.py
nx_neptune/utils/utils.py
nx_neptune-0.4.4.dist-info/licenses/LICENSE
nx_neptune-0.4.4.dist-info/licenses/NOTICE
nx_plugin/__init__.py
nx_plugin/config.py
nx_neptune-0.4.4.dist-info/METADATA
nx_neptune-0.4.4.dist-info/WHEEL
nx_neptune-0.4.4.dist-info/entry_points.txt
nx_neptune-0.4.4.dist-info/top_level.txt
nx_neptune-0.4.4.dist-info/RECORD
