Metadata-Version: 2.4
Name: nx-neptune
Version: 0.4.4
Summary: Neptune computation backend for NetworkX
Author: Amazon Web Services
License: Apache-2.0
Project-URL: Bug Tracker, https://github.com/awslabs/nx-neptune/issues
Project-URL: Source Code, https://github.com/awslabs/nx-neptune
Keywords: networkx,graphs,algorithms,neptune
Platform: Linux
Platform: Mac OSX
Platform: Windows
Platform: Unix
Classifier: Intended Audience :: Developers
Classifier: Intended Audience :: Science/Research
Classifier: License :: OSI Approved :: Apache Software License
Classifier: Operating System :: OS Independent
Classifier: Programming Language :: Python :: 3
Classifier: Programming Language :: Python :: 3.11
Classifier: Programming Language :: Python :: 3.12
Classifier: Programming Language :: Python :: 3.13
Classifier: Programming Language :: Python :: 3 :: Only
Requires-Python: >=3.11
License-File: LICENSE
License-File: NOTICE
Requires-Dist: networkx<4.0.0,>=3.4.2
Requires-Dist: boto3<2.0,>=1.37
Requires-Dist: cymple<1.0.0,>=0.12.0
Provides-Extra: developer
Requires-Dist: pre-commit==3.8.0; extra == "developer"
Requires-Dist: black; extra == "developer"
Requires-Dist: Flake8-pyproject; extra == "developer"
Requires-Dist: mypy; extra == "developer"
Requires-Dist: sphinx; extra == "developer"
Requires-Dist: isort; extra == "developer"
Requires-Dist: pip-licenses; extra == "developer"
Provides-Extra: test
Requires-Dist: pytest>=7.2; extra == "test"
Requires-Dist: pytest-asyncio>=0.26.0; extra == "test"
Requires-Dist: pytest-order>=1.3.0; extra == "test"
Requires-Dist: numpy>=1.23; extra == "test"
Requires-Dist: scipy!=1.11.0,!=1.11.1,>=1.9; extra == "test"
Requires-Dist: pytest-cov; extra == "test"
Requires-Dist: pandas; extra == "test"
Provides-Extra: jupyter
Requires-Dist: jupyter>=1.0.0; extra == "jupyter"
Requires-Dist: notebook>=7.0.0; extra == "jupyter"
Requires-Dist: ipykernel>=6.0.0; extra == "jupyter"
Requires-Dist: matplotlib>=3.0.0; extra == "jupyter"
Requires-Dist: nbstripout>=0.3.10; extra == "jupyter"
Dynamic: license-file
